mz2geohash/__init__.py
mz2geohash/geohash.py
mz2geohash/test_geohash.py
mz2geohash-1.1.0.dist-info/LICENSE.txt
mz2geohash-1.1.0.dist-info/METADATA
mz2geohash-1.1.0.dist-info/WHEEL
mz2geohash-1.1.0.dist-info/top_level.txt
mz2geohash-1.1.0.dist-info/RECORD
