Metadata-Version: 2.1
Name: mz2geohash
Version: 1.1.0
Summary: Mapzen Geohash Fork.  The original is long unmaintained.
Home-page: https://github.com/jason-h-simplifi/mapzen-geohash
Author: Jason Hatton
Author-email: jason@hatton.io
License: License :: OSI Approved :: MIT License
Platform: UNKNOWN
